jnpr/__init__.py
jnpr/healthbot/__init__.py
jnpr/healthbot/_version.py
jnpr/healthbot/exception.py
jnpr/healthbot/healthbot.py
jnpr/healthbot/urlfor.py
jnpr/healthbot/modules/__init__.py
jnpr/healthbot/modules/database.py
jnpr/healthbot/modules/devices.py
jnpr/healthbot/modules/graph.py
jnpr/healthbot/modules/playbooks.py
jnpr/healthbot/modules/profiles.py
jnpr/healthbot/modules/rules.py
jnpr/healthbot/modules/settings.py
jnpr/healthbot/swagger/__init__.py
jnpr/healthbot/swagger/api_client.py
jnpr/healthbot/swagger/configuration.py
jnpr/healthbot/swagger/rest.py
jnpr/healthbot/swagger/api/__init__.py
jnpr/healthbot/swagger/api/administration_api.py
jnpr/healthbot/swagger/api/authentication_api.py
jnpr/healthbot/swagger/api/configuration_api.py
jnpr/healthbot/swagger/api/data_source_api.py
jnpr/healthbot/swagger/api/data_store_api.py
jnpr/healthbot/swagger/api/debug_api.py
jnpr/healthbot/swagger/api/default_api.py
jnpr/healthbot/swagger/api/documentation_api.py
jnpr/healthbot/swagger/api/facts_api.py
jnpr/healthbot/swagger/api/instance_schedule_state_api.py
jnpr/healthbot/swagger/api/license_api.py
jnpr/healthbot/swagger/api/logs_api.py
jnpr/healthbot/swagger/api/organization_api.py
jnpr/healthbot/swagger/api/services_api.py
jnpr/healthbot/swagger/api/system_api.py
jnpr/healthbot/swagger/api/workflow_api.py
jnpr/healthbot/swagger/api/workflow_instance_api.py
jnpr/healthbot/swagger/api/workflow_statistics_api.py
jnpr/healthbot/swagger/models/__init__.py
jnpr/healthbot/swagger/models/affected_groups.py
jnpr/healthbot/swagger/models/apply_macro_schema.py
jnpr/healthbot/swagger/models/applymacro_schema_data.py
jnpr/healthbot/swagger/models/associated_group_schema.py
jnpr/healthbot/swagger/models/associated_role_schema.py
jnpr/healthbot/swagger/models/associated_role_schema_inner.py
jnpr/healthbot/swagger/models/associated_user_schema.py
jnpr/healthbot/swagger/models/associated_user_schema_inner.py
jnpr/healthbot/swagger/models/ca_profile_schema.py
hbez-4.1.0.dist-info/LICENSE
hbez-4.1.0.dist-info/METADATA
hbez-4.1.0.dist-info/WHEEL
hbez-4.1.0.dist-info/top_level.txt
hbez-4.1.0.dist-info/RECORD
