Metadata-Version: 2.1
Name: hbez
Version: 4.1.0
Summary: Healthbot Python Client
Home-page: UNKNOWN
Author: Nitin Kumar
License: Apache 2.0
Keywords: Juniper HealthBot
Platform: UNKNOWN
Classifier: Programming Language :: Python :: 3.4
Classifier: Programming Language :: Python :: 3.5
Classifier: Programming Language :: Python :: 3.6
Classifier: Programming Language :: Python :: 3.7
Classifier: Programming Language :: Python :: 3.8
Classifier: Topic :: System :: Networking
Classifier: Operating System :: OS Independent
Classifier: Topic :: Software Development :: Libraries :: Python Modules
Requires-Python: >=3.4
Requires-Dist: requests
Requires-Dist: first
Requires-Dist: influxdb
Requires-Dist: marshmallow
Requires-Dist: jinja2
Requires-Dist: PyYAML
Requires-Dist: aiohttp
Requires-Dist: certifi (>=14.05.14)
Requires-Dist: six (>=1.10)
Requires-Dist: python-dateutil (>=2.5.3)
Requires-Dist: setuptools (>=21.0.0)
Requires-Dist: urllib3 (>=1.15.1)
Requires-Dist: pyjwt (==1.7.1)
Requires-Dist: uuid
